sliceproofkit/__init__.py
sliceproofkit/apply.py
sliceproofkit/cli.py
sliceproofkit/kit/__init__.py
sliceproofkit/kit/manifest.yaml
sliceproofkit/kit/agents/aider/AIDER_CONVENTIONS.md
sliceproofkit/kit/agents/antigravity/.agent/rules/00-core.md
sliceproofkit/kit/agents/antigravity/.agent/workflows/verify-fast.md
sliceproofkit/kit/agents/claude_code/CLAUDE.md
sliceproofkit/kit/agents/cline/.clinerules/00-core.md
sliceproofkit/kit/agents/codebuddy/CODEBUDDY.md
sliceproofkit/kit/agents/codebuddy/.codebuddy/settings.json
sliceproofkit/kit/agents/codebuddy/.codebuddy/agents/sliceproof.md
sliceproofkit/kit/agents/continue/.continue/rules/00-core.md
sliceproofkit/kit/agents/copilot/.github/copilot-instructions.md
sliceproofkit/kit/agents/cursor/.cursorrules
sliceproofkit/kit/agents/iflow-cli/.iflowignore
sliceproofkit/kit/agents/iflow-cli/IFLOW.md
sliceproofkit/kit/agents/trae/.trae/rules/project_rules.md
sliceproofkit/kit/agents/windsurf/.windsurfrules
sliceproofkit/kit/common/AGENT.md
sliceproofkit/kit/common/LOCKED_FILES.txt
sliceproofkit/kit/common/docs/INDEX.md
sliceproofkit/kit/common/docs/LOGGING.md
sliceproofkit/kit/common/docs/STANDARDS.md
sliceproofkit/kit/common/docs/ADR/0001-template.md
sliceproofkit/kit/common/gitignore/snippet.txt
sliceproofkit/kit/common/logs/.gitkeep
sliceproofkit/kit/common/memory/INDEX.md
sliceproofkit/kit/common/memory/STM.md
sliceproofkit/kit/common/memory/LTM/0000-LTM_OVERVIEW.md
sliceproofkit/kit/common/scripts/check_locked.sh
sliceproofkit/kit/common/scripts/check_memory.py
sliceproofkit/kit/common/scripts/check_memory.sh
sliceproofkit/kit/common/scripts/check_outputs.py
sliceproofkit/kit/common/scripts/check_outputs.sh
sliceproofkit/kit/common/scripts/grep_logs.sh
sliceproofkit/kit/common/scripts/kgrep.sh
sliceproofkit/kit/common/scripts/lint_gate.sh
sliceproofkit/kit/common/scripts/run_with_log.sh
sliceproofkit/kit/common/scripts/verify_fast.sh
sliceproofkit/kit/common/scripts/verify_full.sh
sliceproofkit-0.1.2.dist-info/licenses/LICENSE
sliceproofkit-0.1.2.dist-info/METADATA
sliceproofkit-0.1.2.dist-info/WHEEL
sliceproofkit-0.1.2.dist-info/entry_points.txt
sliceproofkit-0.1.2.dist-info/top_level.txt
sliceproofkit-0.1.2.dist-info/RECORD
